CHANGELOG.txt
LICENSE.txt
MANIFEST.in
README.txt
ez_setup.py
setup.cfg
setup.py
AppDispatch.egg-info/PKG-INFO
AppDispatch.egg-info/SOURCES.txt
AppDispatch.egg-info/dependency_links.txt
AppDispatch.egg-info/entry_points.txt
AppDispatch.egg-info/not-zip-safe
AppDispatch.egg-info/requires.txt
AppDispatch.egg-info/top_level.txt
appdispatch/__init__.py
doc/Makefile
doc/index.txt
doc/source/api.rst
doc/source/conf.py
doc/source/index.rst
doc/source/manual.rst
example/README.txt
test/README.txt
test/doc.py