Metadata-Version: 1.0
Name: AppDispatch
Version: 0.3.3
Summary: Builds upon a PipeStack architecture to provide a nice way of writing apps
Home-page: http://jimmyg.org/work/code/appdispatch/index.html
Author: James Gardner
Author-email: james@<package hompage domain>
License: GNU AGPLv3
Platform: UNKNOWN
Classifier: Development Status :: 3 - Alpha
Classifier: License :: OSI Approved :: GNU Affero General Public License v3
Classifier: Programming Language :: Python
